initdi/__init__.py
initdi/core.py
initdi/decorators.py
initdi/ext/__init__.py
initdi/ext/fastapi.py
initdi/ext/starlette/__init__.py
initdi/ext/starlette/middleware.py
initdi/ext/utils.py
initdi/py.typed
initdi/utils.py
pyxdi/__init__.py
initdi-0.19.0.dist-info/LICENSE
initdi-0.19.0.dist-info/METADATA
initdi-0.19.0.dist-info/WHEEL
initdi-0.19.0.dist-info/RECORD
