Metadata-Version: 2.1
Name: initdi
Version: 0.19.0
Summary: Dependency Injection library
Home-page: https://github.com/antonrh/initdi
License: MIT
Keywords: dependency injection,dependencies,di,async,asyncio,application
Author: Anton Ruhlov
Author-email: antonruhlov@gmail.com
Requires-Python: >=3.8,<4.0
Classifier: Development Status :: 5 - Production/Stable
Classifier: Environment :: Web Environment
Classifier: Intended Audience :: Developers
Classifier: Intended Audience :: Information Technology
Classifier: Intended Audience :: System Administrators
Classifier: License :: OSI Approved :: MIT License
Classifier: Operating System :: OS Independent
Classifier: Programming Language :: Python :: 3
Classifier: Programming Language :: Python :: 3.8
Classifier: Programming Language :: Python :: 3.9
Classifier: Programming Language :: Python :: 3.10
Classifier: Programming Language :: Python :: 3.11
Classifier: Programming Language :: Python :: 3.12
Classifier: Programming Language :: Python :: 3 :: Only
Classifier: Programming Language :: Python :: 3.7
Classifier: Topic :: Internet
Classifier: Topic :: Software Development
Classifier: Topic :: Software Development :: Libraries
Classifier: Topic :: Software Development :: Libraries :: Application Frameworks
Classifier: Topic :: Software Development :: Libraries :: Python Modules
Classifier: Typing :: Typed
Provides-Extra: async
Provides-Extra: docs
Requires-Dist: anyio (>=3.6.2,<4.0.0) ; extra == "async"
Requires-Dist: mkdocs (>=1.4.2,<2.0.0) ; extra == "docs"
Requires-Dist: mkdocs-material (>=9.1.13,<10.0.0) ; extra == "docs"
Project-URL: Repository, https://github.com/antonrh/initdi
